Metadata-Version: 2.1
Name: dappy-drf-extensions
Version: 0.4.0
Summary: Extensions for Django REST Framework
Home-page: http://github.com/chibisov/drf-extensions
Author: Gennady Chibisov
Author-email: web-chib@ya.ru
License: BSD
Download-URL: https://pypi.python.org/pypi/drf-extensions/
Platform: UNKNOWN
Classifier: Development Status :: 5 - Production/Stable
Classifier: Environment :: Web Environment
Classifier: Framework :: Django
Classifier: Intended Audience :: Developers
Classifier: License :: OSI Approved :: MIT License
Classifier: Operating System :: OS Independent
Classifier: Programming Language :: Python
Classifier: Programming Language :: Python :: 3
Classifier: Topic :: Internet :: WWW/HTTP
Requires-Dist: djangorestframework (>=3.8.1)
